DesignFiles/PmodAD1Ctrl.sv
/*
    Author: Grant Chapman

    Date Created: 2026-08-21
    Project Name: Oscilloscope
    Module Name: PmodAD1Ctrl

    Description: 
    Interfaces with Digilent's Pmod AD1 analog to digital converter using an SPI-like protocol. The
    major difference from SPI is instead of a MOSI and MISO line, there are 2 MISO lines, each interacting
    with one of the ADCs onboard.

    Dependencies: N/A
    
    Revision History: 
    Revision 1.0  - Initial Design.
*/

module PmodAD1Ctrl (
    input  logic        clk_fpga, // 25 MHz clock from board
    input  logic        rst_n,    // Active low reset
    input  logic        miso_0,   // data in 0
    input  logic        miso_1,   // data in 1
    output logic        sclk,     // serial clock
    output logic        cs_n,     // chip select
    output logic [11:0] data_ch0, // ch0 out
    output logic [11:0] data_ch1, // ch1 out
    output logic        valid     // data valid signal
);

    logic        clk_pmod;
    logic [4:0]  bit_count;
    logic [11:0] shift_reg_0;
    logic [11:0] shift_reg_1;

    // Divide 25 MHz clock to 12.5 MHz. Maximum ADC clock is 20MHz.
    always_ff @(posedge clk_fpga or negedge rst_n) begin
        if (!rst_n) begin
            clk_pmod <= 1'b0;
        end else begin
            clk_pmod <= ~clk_pmod;
        end
    end

    //The ADC has a SPI CPOL of 1, so sclk idles at 1 when CS is inactive.
    assign sclk = (cs_n == 1'b0) ? clk_pmod : 1'b1;

    // Control the SPI transcation.
    always_ff @(posedge clk_pmod or negedge rst_n) begin
        if (!rst_n) begin
            cs_n        <= 1'b1;
            bit_count   <= 5'd0;
            valid       <= 1'b0;
            data_ch0    <= 12'd0;
            data_ch1    <= 12'd0;
            shift_reg_0 <= 12'd0;
            shift_reg_0 <= 12'd0;
        end else begin
            if (bit_count == 5'd0) begin
                //Start recieving
                cs_n  <= 1'b0;
                valid <= 1'b0;
                bit_count <= bit_count + 1'b1;
            end else if (bit_count <= 5'd16) begin
                //Continue recieving
                shift_reg_0 <= {shift_reg_0[10:0], miso_0};
                shift_reg_1 <= {shift_reg_1[10:0], miso_1};
                bit_count   <= bit_count + 1'b1;
            end else begin
                //End recieving
                cs_n      <= 1'b1;
                data_ch0  <= shift_reg_0;
                data_ch1  <= shift_reg_1;
                valid     <= 1'b1;
                bit_count <= 5'd0;
            end
        end
    end
    
endmodule

DesignFiles/PmodAD1_top.sv
/*
    Author: Grant Chapman

    Date Created: 2026-08-21
    Project Name: Oscilloscope
    Module Name: PmodAD1_top

    Description: 
    A top module instantiating the Pmod AD1 control module, and displaying the input on a
    seven segment display. Uses the Double Dabble algorithm to convert the 12-bit binary
    output from the ADC into a decimal for display on a seven segment.

    Dependencies: SevenSegDriver.sv
                  PmodAD1Ctrl.sv
    
    Revision History: 1.0  - Initial Design
                      1.01 - Updated Output conditions - led
    */

    module PmodAD1_top (
        input  logic       clk,
        input  logic       rst_p, //Positive reset
        input  logic       miso_0,
        input  logic       miso_1,
        output logic       sclk,
        output logic       cs_n,
        output logic       led1
    );
    
    /* verilator lint_off UNUSEDSIGNAL */
    logic [11:0] data_ch0;
    logic [11:0] data_ch1;
    logic        valid;
    /* verilator lint_on UNUSEDSIGNAL */
    
    PmodAD1Ctrl ctrl (
        .clk_fpga(clk),
        .miso_0(miso_0),
        .miso_1(miso_1),
        .rst_n(~rst_p),

        .sclk(sclk),
        .cs_n(cs_n),
        .data_ch0(data_ch0),
        .data_ch1(data_ch1),
        .valid(valid)
    );
    
    //Turn on led 1 if input is greater than 1/4 of the supply voltage
    always_comb begin
        led1 = (data_ch0 > 1024) ? 1'b1 : 1'b0;
    end

    endmodule

TestFiles/oscilloscope_waveform.vcd
$version Generated by VerilatedVcd $end
$timescale 1ps $end
 $scope module TOP $end
  $var wire 1 ) clk $end
  $var wire 1 * rst_p $end
  $var wire 1 + miso_0 $end
  $var wire 1 , miso_1 $end
  $var wire 1 - sclk $end
  $var wire 1 . cs_n $end
  $var wire 1 / led1 $end
  $scope module PmodAD1_top $end
   $var wire 1 ) clk $end
   $var wire 1 * rst_p $end
   $var wire 1 + miso_0 $end
   $var wire 1 , miso_1 $end
   $var wire 1 - sclk $end
   $var wire 1 . cs_n $end
   $var wire 1 / led1 $end
   $var wire 12 # data_ch0 [11:0] $end
   $var wire 12 $ data_ch1 [11:0] $end
   $var wire 1 % valid $end
   $scope module ctrl $end
    $var wire 1 ) clk_fpga $end
    $var wire 1 0 rst_n $end
    $var wire 1 + miso_0 $end
    $var wire 1 , miso_1 $end
    $var wire 1 - sclk $end
    $var wire 1 . cs_n $end
    $var wire 12 # data_ch0 [11:0] $end
    $var wire 12 $ data_ch1 [11:0] $end
    $var wire 1 % valid $end
    $var wire 1 1 clk_pmod $end
    $var wire 5 & bit_count [4:0] $end
    $var wire 12 ' shift_reg_0 [11:0] $end
    $var wire 12 ( shift_reg_1 [11:0] $end
   $upscope $end
  $upscope $end
 $upscope $end
$enddefinitions $end


#0
b000000000000 #
b000000000000 $
0%
b00000 &
b000000000000 '
b000000000000 (
1)
1*
0+
0,
0-
0.
0/
00
01
#1
0)
#2
1)
#3
0)
#4
1)
#5
0)
#6
1)
#7
0)
#8
1)
#9
0)
#10
1)
#11
0)
#12
1)
#13
0)
#14
1)
#15
0)
#16
1)
#17
0)
#18
1)
#19
0)
#20
1)
#21
0)
0*
10
#22
b00001 &
1)
1-
11
#23
0)
#24
1)
0-
01
#25
0)
#26
b00010 &
1)
1-
11
#27
0)
#28
1)
0-
01
#29
0)
#30
b00011 &
1)
1-
11
#31
0)
#32
1)
0-
01
#33
0)
#34
b00100 &
1)
1-
11
#35
0)
#36
1)
0-
01
#37
0)
#38
b00101 &
1)
1-
11
#39
0)
#40
1)
0-
01
#41
0)
#42
b00110 &
1)
1-
11
#43
0)
#44
1)
0-
01
#45
0)
#46
b00111 &
1)
1-
11
#47
0)
#48
1)
0-
01
#49
0)
#50
b01000 &
1)
1-
11
#51
0)
1+
#52
1)
0-
01
#53
0)
#54
b01001 &
b000000000001 '
1)
1-
11
#55
0)
#56
1)
0-
01
#57
0)
#58
b01010 &
b000000000011 '
1)
1-
11
#59
0)
#60
1)
0-
01
#61
0)
0+
1,
#62
b01011 &
b000000000110 '
b000000000001 (
1)
1-
11
#63
0)
#64
1)
0-
01
#65
0)
#66
b01100 &
b000000001100 '
b000000000011 (
1)
1-
11
#67
0)
#68
1)
0-
01
#69
0)
#70
b01101 &
b000000011000 '
b000000000111 (
1)
1-
11
#71
0)
1+
0,
#72
1)
0-
01
#73
0)
#74
b01110 &
b000000110001 '
b000000001110 (
1)
1-
11
#75
0)
#76
1)
0-
01
#77
0)
#78
b01111 &
b000001100011 '
b000000011100 (
1)
1-
11
#79
0)
#80
1)
0-
01
#81
0)
0+
1,
#82
b10000 &
b000011000110 '
b000000111001 (
1)
1-
11
#83
0)
#84
1)
0-
01
#85
0)
#86
b10001 &
b000110001100 '
b000001110011 (
1)
1-
11
#87
0)
#88
1)
0-
01
#89
0)
#90
b000110001100 #
b000001110011 $
1%
b00000 &
1)
1-
1.
11
#91
0)
#92
1)
01
#93
0)
#94
0%
b00001 &
1)
0.
11
#95
0)
1+
0,
#96
1)
0-
01
#97
0)
#98
b00010 &
b001100011001 '
b000011100110 (
1)
1-
11
#99
0)
#100
1)
0-
01
#101
0)
0+
1,
#102
b00011 &
b011000110010 '
b000111001101 (
1)
1-
11
#103
0)
#104
1)
0-
01
#105
0)
#106
b00100 &
b110001100100 '
b001110011011 (
1)
1-
11
#107
0)
#108
1)
0-
01
#109
0)
#110
b00101 &
b100011001000 '
b011100110111 (
1)
1-
11
#111
0)
1+
0,
#112
1)
0-
01
#113
0)
#114
b00110 &
b000110010001 '
b111001101110 (
1)
1-
11
#115
0)
#116
1)
0-
01
#117
0)
#118
b00111 &
b001100100011 '
b110011011100 (
1)
1-
11
#119
0)
#120
1)
0-
01
#121
0)
0+
1,
#122
b01000 &
b011001000110 '
b100110111001 (
1)
1-
11
#123
0)
#124
1)
0-
01
#125
0)
#126
b01001 &
b110010001100 '
b001101110011 (
1)
1-
11
#127
0)
#128
1)
0-
01
#129
0)
#130
b01010 &
b100100011000 '
b011011100111 (
1)
1-
11
#131
0)
1+
0,
#132
1)
0-
01
#133
0)
#134
b01011 &
b001000110001 '
b110111001110 (
1)
1-
11
#135
0)
#136
1)
0-
01
#137
0)
#138
b01100 &
b010001100011 '
b101110011100 (
1)
1-
11
#139
0)
#140
1)
0-
01
#141
0)
0+
1,
#142
b01101 &
b100011000110 '
b011100111001 (
1)
1-
11
#143
0)
#144
1)
0-
01
#145
0)
#146
b01110 &
b000110001100 '
b111001110011 (
1)
1-
11
#147
0)
#148
1)
0-
01
#149
0)
#150
b01111 &
b001100011000 '
b110011100111 (
1)
1-
11
#151
0)
1+
0,
#152
1)
0-
01
#153
0)
#154
b10000 &
b011000110001 '
b100111001110 (
1)
1-
11
#155
0)
#156
1)
0-
01
#157
0)
#158
b10001 &
b110001100011 '
b001110011100 (
1)
1-
11
#159
0)
#160
1)
0-
01
#161
0)
0+
1,
#162
b110001100011 #
b001110011100 $
1%
b00000 &
1)
1-
1.
1/
11
#163
0)
#164
1)
01
#165
0)
#166
0%
b00001 &
1)
0.
11
#167
0)
#168
1)
0-
01
#169
0)
#170
b00010 &
b100011000110 '
b011100111001 (
1)
1-
11
#171
0)
1+
0,
#172
1)
0-
01
#173
0)
#174
b00011 &
b000110001101 '
b111001110010 (
1)
1-
11
#175
0)
#176
1)
0-
01
#177
0)
#178
b00100 &
b001100011011 '
b110011100100 (
1)
1-
11
#179
0)
#180
1)
0-
01
#181
0)
0+
1,
#182
b00101 &
b011000110110 '
b100111001001 (
1)
1-
11
#183
0)
#184
1)
0-
01
#185
0)
#186
b00110 &
b110001101100 '
b001110010011 (
1)
1-
11
#187
0)
#188
1)
0-
01
#189
0)
#190
b00111 &
b100011011000 '
b011100100111 (
1)
1-
11
#191
0)
1+
0,
#192
1)
0-
01
#193
0)
#194
b01000 &
b000110110001 '
b111001001110 (
1)
1-
11
#195
0)
#196
1)
0-
01
#197
0)
#198
b01001 &
b001101100011 '
b110010011100 (
1)
1-
11
#199
0)
#200
1)
0-
01
#201
0)
0+
1,
#202
b01010 &
b011011000110 '
b100100111001 (
1)
1-
11
#203
0)
#204
1)
0-
01
#205
0)
#206
b01011 &
b110110001100 '
b001001110011 (
1)
1-
11
#207
0)
#208
1)
0-
01
#209
0)
#210
b01100 &
b101100011000 '
b010011100111 (
1)
1-
11
#211
0)
1+
0,
#212
1)
0-
01
#213
0)
#214
b01101 &
b011000110001 '
b100111001110 (
1)
1-
11
#215
0)
#216
1)
0-
01
#217
0)
#218
b01110 &
b110001100011 '
b001110011100 (
1)
1-
11
#219
0)
#220
1)
0-
01
#221
0)
0+
1,
#222
b01111 &
b100011000110 '
b011100111001 (
1)
1-
11
#223
0)
#224
1)
0-
01
#225
0)
#226
b10000 &
b000110001100 '
b111001110011 (
1)
1-
11
#227
0)
#228
1)
0-
01
#229
0)
#230
b10001 &
b001100011000 '
b110011100111 (
1)
1-
11
#231
0)
1+
0,
#232
1)
0-
01
#233
0)
#234
b001100011000 #
b110011100111 $
1%
b00000 &
1)
1-
1.
0/
11
#235
0)
#236
1)
01
#237
0)
#238
0%
b00001 &
1)
0.
11
#239
0)
#240
1)
0-
01
#241
0)
0+
1,
#242
b00010 &
b011000110000 '
b100111001111 (
1)
1-
11
#243
0)
#244
1)
0-
01
#245
0)
#246
b00011 &
b110001100000 '
b001110011111 (
1)
1-
11
#247
0)
#248
1)
0-
01
#249
0)
#250
b00100 &
b100011000000 '
b011100111111 (
1)
1-
11
#251
0)
1+
0,
#252
1)
0-
01
#253
0)
#254
b00101 &
b000110000001 '
b111001111110 (
1)
1-
11
#255
0)
#256
1)
0-
01
#257
0)
#258
b00110 &
b001100000011 '
b110011111100 (
1)
1-
11
#259
0)
#260
1)
0-
01
#261
0)
0+
1,
#262
b00111 &
b011000000110 '
b100111111001 (
1)
1-
11
#263
0)
#264
1)
0-
01
#265
0)
#266
b01000 &
b110000001100 '
b001111110011 (
1)
1-
11
#267
0)
#268
1)
0-
01
#269
0)
#270
b01001 &
b100000011000 '
b011111100111 (
1)
1-
11
#271
0)
1+
0,
#272
1)
0-
01
#273
0)
#274
b01010 &
b000000110001 '
b111111001110 (
1)
1-
11
#275
0)
#276
1)
0-
01
#277
0)
#278
b01011 &
b000001100011 '
b111110011100 (
1)
1-
11
#279
0)
#280
1)
0-
01
#281
0)
0+
1,
#282
b01100 &
b000011000110 '
b111100111001 (
1)
1-
11
#283
0)
#284
1)
0-
01
#285
0)
#286
b01101 &
b000110001100 '
b111001110011 (
1)
1-
11
#287
0)
#288
1)
0-
01
#289
0)
#290
b01110 &
b001100011000 '
b110011100111 (
1)
1-
11
#291
0)
1+
0,
#292
1)
0-
01
#293
0)
#294
b01111 &
b011000110001 '
b100111001110 (
1)
1-
11
#295
0)
#296
1)
0-
01
#297
0)
#298
b10000 &
b110001100011 '
b001110011100 (
1)
1-
11
#299
0)
#300
1)
0-
01
#301
0)
0+
1,
#302
b10001 &
b100011000110 '
b011100111001 (
1)
1-
11
#303
0)
#304
1)
0-
01
#305
0)
#306
b100011000110 #
b011100111001 $
1%
b00000 &
1)
1-
1.
1/
11
#307
0)
#308
1)
01
#309
0)
#310
0%
b00001 &
1)
0.
11
#311
0)
1+
0,
#312
1)
0-
01
#313
0)
#314
b00010 &
b000110001101 '
b111001110010 (
1)
1-
11
#315
0)
#316
1)
0-
01
#317
0)
#318
b00011 &
b001100011011 '
b110011100100 (
1)
1-
11
#319
0)
#320
1)
0-
01
#321
0)
0+
1,
#322
b00100 &
b011000110110 '
b100111001001 (
1)
1-
11
#323
0)
#324
1)
0-
01
#325
0)
#326
b00101 &
b110001101100 '
b001110010011 (
1)
1-
11
#327
0)
#328
1)
0-
01
#329
0)
#330
b00110 &
b100011011000 '
b011100100111 (
1)
1-
11
#331
0)
1+
0,
#332
1)
0-
01
#333
0)
#334
b00111 &
b000110110001 '
b111001001110 (
1)
1-
11
#335
0)
#336
1)
0-
01
#337
0)
#338
b01000 &
b001101100011 '
b110010011100 (
1)
1-
11
#339
0)
#340
1)
0-
01
#341
0)
0+
1,
#342
b01001 &
b011011000110 '
b100100111001 (
1)
1-
11
#343
0)
#344
1)
0-
01
#345
0)
#346
b01010 &
b110110001100 '
b001001110011 (
1)
1-
11
#347
0)
#348
1)
0-
01
#349
0)
#350
b01011 &
b101100011000 '
b010011100111 (
1)
1-
11
#351
0)
1+
0,
#352
1)
0-
01
#353
0)
#354
b01100 &
b011000110001 '
b100111001110 (
1)
1-
11
#355
0)
#356
1)
0-
01
#357
0)
#358
b01101 &
b110001100011 '
b001110011100 (
1)
1-
11
#359
0)
#360
1)
0-
01
#361
0)
0+
1,
#362
b01110 &
b100011000110 '
b011100111001 (
1)
1-
11
#363
0)
#364
1)
0-
01
#365
0)
#366
b01111 &
b000110001100 '
b111001110011 (
1)
1-
11
#367
0)
#368
1)
0-
01
#369
0)
#370
b10000 &
b001100011000 '
b110011100111 (
1)
1-
11
#371
0)
1+
0,
#372
1)
0-
01
#373
0)
#374
b10001 &
b011000110001 '
b100111001110 (
1)
1-
11
#375
0)
#376
1)
0-
01
#377
0)
#378
b011000110001 #
b100111001110 $
1%
b00000 &
1)
1-
1.
11
#379
0)
#380
1)
01
#381
0)
#382
0%
b00001 &
1)
0.
11
#383
0)
0+
1,
#384
1)
0-
01
#385
0)
#386
b00010 &
b110001100010 '
b001110011101 (
1)
1-
11
#387
0)
#388
1)
0-
01
#389
0)
#390
b00011 &
b100011000100 '
b011100111011 (
1)
1-
11
#391
0)
1+
0,
#392
1)
0-
01
#393
0)
#394
b00100 &
b000110001001 '
b111001110110 (
1)
1-
11
#395
0)
#396
1)
0-
01
#397
0)
#398
b00101 &
b001100010011 '
b110011101100 (
1)
1-
11
#399
0)
#400
1)
0-
01
#401
0)
0+
1,
#402
b00110 &
b011000100110 '
b100111011001 (
1)
1-
11
#403
0)
#404
1)
0-
01
#405
0)
#406
b00111 &
b110001001100 '
b001110110011 (
1)
1-
11
#407
0)
#408
1)
0-
01
#409
0)
#410
b01000 &
b100010011000 '
b011101100111 (
1)
1-
11
#411
0)
1+
0,
#412
1)
0-
01
#413
0)
#414
b01001 &
b000100110001 '
b111011001110 (
1)
1-
11
#415
0)
#416
1)
0-
01
#417
0)
#418
b01010 &
b001001100011 '
b110110011100 (
1)
1-
11
#419
0)
#420
1)
0-
01
#421
0)
0+
1,
#422
b01011 &
b010011000110 '
b101100111001 (
1)
1-
11
#423
0)
#424
1)
0-
01
#425
0)
#426
b01100 &
b100110001100 '
b011001110011 (
1)
1-
11
#427
0)
#428
1)
0-
01
#429
0)
#430
b01101 &
b001100011000 '
b110011100111 (
1)
1-
11
#431
0)
1+
0,
#432
1)
0-
01
#433
0)
#434
b01110 &
b011000110001 '
b100111001110 (
1)
1-
11
#435
0)
#436
1)
0-
01
#437
0)
#438
b01111 &
b110001100011 '
b001110011100 (
1)
1-
11
#439
0)
#440
1)
0-
01
#441
0)
0+
1,
#442
b10000 &
b100011000110 '
b011100111001 (
1)
1-
11
#443
0)
#444
1)
0-
01
#445
0)
#446
b10001 &
b000110001100 '
b111001110011 (
1)
1-
11
#447
0)
#448
1)
0-
01
#449
0)
#450
b000110001100 #
b111001110011 $
1%
b00000 &
1)
1-
1.
0/
11
#451
0)
#452
1)
01
#453
0)
#454
0%
b00001 &
1)
0.
11
#455
0)
1+
0,
#456
1)
0-
01
#457
0)
#458
b00010 &
b001100011001 '
b110011100110 (
1)
1-
11
#459
0)
#460
1)
0-
01
#461
0)
0+
1,
#462
b00011 &
b011000110010 '
b100111001101 (
1)
1-
11
#463
0)
#464
1)
0-
01
#465
0)
#466
b00100 &
b110001100100 '
b001110011011 (
1)
1-
11
#467
0)
#468
1)
0-
01
#469
0)
#470
b00101 &
b100011001000 '
b011100110111 (
1)
1-
11
#471
0)
1+
0,
#472
1)
0-
01
#473
0)
#474
b00110 &
b000110010001 '
b111001101110 (
1)
1-
11
#475
0)
#476
1)
0-
01
#477
0)
#478
b00111 &
b001100100011 '
b110011011100 (
1)
1-
11
#479
0)
#480
1)
0-
01
#481
0)
0+
1,
#482
b01000 &
b011001000110 '
b100110111001 (
1)
1-
11
#483
0)
#484
1)
0-
01
#485
0)
#486
b01001 &
b110010001100 '
b001101110011 (
1)
1-
11
#487
0)
#488
1)
0-
01
#489
0)
#490
b01010 &
b100100011000 '
b011011100111 (
1)
1-
11
#491
0)
1+
0,
#492
1)
0-
01
#493
0)
#494
b01011 &
b001000110001 '
b110111001110 (
1)
1-
11
#495
0)
#496
1)
0-
01
#497
0)
#498
b01100 &
b010001100011 '
b101110011100 (
1)
1-
11
#499
0)
#500
1)
0-
01
#501
0)
0+
1,
#502
b01101 &
b100011000110 '
b011100111001 (
1)
1-
11
#503
0)
#504
1)
0-
01
#505
0)
#506
b01110 &
b000110001100 '
b111001110011 (
1)
1-
11
#507
0)
#508
1)
0-
01
#509
0)
#510
b01111 &
b001100011000 '
b110011100111 (
1)
1-
11
#511
0)
1+
0,
#512
1)
0-
01
#513
0)
#514
b10000 &
b011000110001 '
b100111001110 (
1)
1-
11
#515
0)
#516
1)
0-
01
#517
0)
#518
b10001 &
b110001100011 '
b001110011100 (
1)
1-
11
#519
0)
#520
1)
0-
01
#521
0)
0+
1,
#522
b110001100011 #
b001110011100 $
1%
b00000 &
1)
1-
1.
1/
11
#523
0)
#524
1)
01
#525
0)
#526
0%
b00001 &
1)
0.
11
#527
0)
#528
1)
0-
01
#529
0)
#530
b00010 &
b100011000110 '
b011100111001 (
1)
1-
11
#531
0)
1+
0,
#532
1)
0-
01
#533
0)
#534
b00011 &
b000110001101 '
b111001110010 (
1)
1-
11
#535
0)
#536
1)
0-
01
#537
0)
#538
b00100 &
b001100011011 '
b110011100100 (
1)
1-
11
#539
0)
#540
1)
0-
01
#541
0)
0+
1,
#542
b00101 &
b011000110110 '
b100111001001 (
1)
1-
11
#543
0)
#544
1)
0-
01
#545
0)
#546
b00110 &
b110001101100 '
b001110010011 (
1)
1-
11
#547
0)
#548
1)
0-
01
#549
0)
#550
b00111 &
b100011011000 '
b011100100111 (
1)
1-
11
#551
0)
1+
0,
#552
1)
0-
01
#553
0)
#554
b01000 &
b000110110001 '
b111001001110 (
1)
1-
11
#555
0)
#556
1)
0-
01
#557
0)
#558
b01001 &
b001101100011 '
b110010011100 (
1)
1-
11
#559
0)
#560
1)
0-
01
#561
0)
0+
1,
#562
b01010 &
b011011000110 '
b100100111001 (
1)
1-
11
#563
0)
#564
1)
0-
01
#565
0)
#566
b01011 &
b110110001100 '
b001001110011 (
1)
1-
11
#567
0)
#568
1)
0-
01
#569
0)
#570
b01100 &
b101100011000 '
b010011100111 (
1)
1-
11
#571
0)
1+
0,
#572
1)
0-
01
#573
0)
#574
b01101 &
b011000110001 '
b100111001110 (
1)
1-
11
#575
0)
#576
1)
0-
01
#577
0)
#578
b01110 &
b110001100011 '
b001110011100 (
1)
1-
11
#579
0)
#580
1)
0-
01
#581
0)
0+
1,
#582
b01111 &
b100011000110 '
b011100111001 (
1)
1-
11
#583
0)
#584
1)
0-
01
#585
0)
#586
b10000 &
b000110001100 '
b111001110011 (
1)
1-
11
#587
0)
#588
1)
0-
01
#589
0)
#590
b10001 &
b001100011000 '
b110011100111 (
1)
1-
11
#591
0)
1+
0,
#592
1)
0-
01
#593
0)
#594
b001100011000 #
b110011100111 $
1%
b00000 &
1)
1-
1.
0/
11
#595
0)
#596
1)
01
#597
0)
#598
0%
b00001 &
1)
0.
11
#599
0)
#600
1)
0-
01
#601
0)
0+
1,
#602
b00010 &
b011000110000 '
b100111001111 (
1)
1-
11
#603
0)
#604
1)
0-
01
#605
0)
#606
b00011 &
b110001100000 '
b001110011111 (
1)
1-
11
#607
0)
#608
1)
0-
01
#609
0)
#610
b00100 &
b100011000000 '
b011100111111 (
1)
1-
11
#611
0)
1+
0,
#612
1)
0-
01
#613
0)
#614
b00101 &
b000110000001 '
b111001111110 (
1)
1-
11
#615
0)
#616
1)
0-
01
#617
0)
#618
b00110 &
b001100000011 '
b110011111100 (
1)
1-
11
#619
0)
#620
1)
0-
01
#621
0)
0+
1,
#622
b00111 &
b011000000110 '
b100111111001 (
1)
1-
11
#623
0)
#624
1)
0-
01
#625
0)
#626
b01000 &
b110000001100 '
b001111110011 (
1)
1-
11
#627
0)
#628
1)
0-
01
#629
0)
#630
b01001 &
b100000011000 '
b011111100111 (
1)
1-
11
#631
0)
1+
0,
#632
1)
0-
01
#633
0)
#634
b01010 &
b000000110001 '
b111111001110 (
1)
1-
11
#635
0)
#636
1)
0-
01
#637
0)
#638
b01011 &
b000001100011 '
b111110011100 (
1)
1-
11
#639
0)
#640
1)
0-
01
#641
0)
0+
1,
#642
b01100 &
b000011000110 '
b111100111001 (
1)
1-
11
#643
0)
#644
1)
0-
01
#645
0)
#646
b01101 &
b000110001100 '
b111001110011 (
1)
1-
11
#647
0)
#648
1)
0-
01
#649
0)
#650
b01110 &
b001100011000 '
b110011100111 (
1)
1-
11
#651
0)
1+
0,
#652
1)
0-
01
#653
0)
#654
b01111 &
b011000110001 '
b100111001110 (
1)
1-
11
#655
0)
#656
1)
0-
01
#657
0)
#658
b10000 &
b110001100011 '
b001110011100 (
1)
1-
11
#659
0)
#660
1)
0-
01
#661
0)
0+
1,
#662
b10001 &
b100011000110 '
b011100111001 (
1)
1-
11
#663
0)
#664
1)
0-
01
#665
0)
#666
b100011000110 #
b011100111001 $
1%
b00000 &
1)
1-
1.
1/
11
#667
0)
#668
1)
01
#669
0)
#670
0%
b00001 &
1)
0.
11
#671
0)
1+
0,
#672
1)
0-
01
#673
0)
#674
b00010 &
b000110001101 '
b111001110010 (
1)
1-
11
#675
0)
#676
1)
0-
01
#677
0)
#678
b00011 &
b001100011011 '
b110011100100 (
1)
1-
11
#679
0)
#680
1)
0-
01
#681
0)
0+
1,
#682
b00100 &
b011000110110 '
b100111001001 (
1)
1-
11
#683
0)
#684
1)
0-
01
#685
0)
#686
b00101 &
b110001101100 '
b001110010011 (
1)
1-
11
#687
0)
#688
1)
0-
01
#689
0)
#690
b00110 &
b100011011000 '
b011100100111 (
1)
1-
11
#691
0)
1+
0,
#692
1)
0-
01
#693
0)
#694
b00111 &
b000110110001 '
b111001001110 (
1)
1-
11
#695
0)
#696
1)
0-
01
#697
0)
#698
b01000 &
b001101100011 '
b110010011100 (
1)
1-
11
#699
0)
#700
1)
0-
01
#701
0)
0+
1,
#702
b01001 &
b011011000110 '
b100100111001 (
1)
1-
11
#703
0)
#704
1)
0-
01
#705
0)
#706
b01010 &
b110110001100 '
b001001110011 (
1)
1-
11
#707
0)
#708
1)
0-
01
#709
0)
#710
b01011 &
b101100011000 '
b010011100111 (
1)
1-
11
#711
0)
1+
0,
#712
1)
0-
01
#713
0)
#714
b01100 &
b011000110001 '
b100111001110 (
1)
1-
11
#715
0)
#716
1)
0-
01
#717
0)
#718
b01101 &
b110001100011 '
b001110011100 (
1)
1-
11
#719
0)
#720
1)
0-
01
#721
0)
0+
1,
#722
b01110 &
b100011000110 '
b011100111001 (
1)
1-
11
#723
0)
#724
1)
0-
01
#725
0)
#726
b01111 &
b000110001100 '
b111001110011 (
1)
1-
11
#727
0)
#728
1)
0-
01
#729
0)
#730
b10000 &
b001100011000 '
b110011100111 (
1)
1-
11
#731
0)
1+
0,
#732
1)
0-
01
#733
0)
#734
b10001 &
b011000110001 '
b100111001110 (
1)
1-
11
#735
0)
#736
1)
0-
01
#737
0)
#738
b011000110001 #
b100111001110 $
1%
b00000 &
1)
1-
1.
11
#739
0)
#740
1)
01
#741
0)
#742
0%
b00001 &
1)
0.
11
#743
0)
0+
1,
#744
1)
0-
01
#745
0)
#746
b00010 &
b110001100010 '
b001110011101 (
1)
1-
11
#747
0)
#748
1)
0-
01
#749
0)
#750
b00011 &
b100011000100 '
b011100111011 (
1)
1-
11
#751
0)
1+
0,
#752
1)
0-
01
#753
0)
#754
b00100 &
b000110001001 '
b111001110110 (
1)
1-
11
#755
0)
#756
1)
0-
01
#757
0)
#758
b00101 &
b001100010011 '
b110011101100 (
1)
1-
11
#759
0)
#760
1)
0-
01
#761
0)
0+
1,
#762
b00110 &
b011000100110 '
b100111011001 (
1)
1-
11
#763
0)
#764
1)
0-
01
#765
0)
#766
b00111 &
b110001001100 '
b001110110011 (
1)
1-
11
#767
0)
#768
1)
0-
01
#769
0)
#770
b01000 &
b100010011000 '
b011101100111 (
1)
1-
11
#771
0)
1+
0,
#772
1)
0-
01
#773
0)
#774
b01001 &
b000100110001 '
b111011001110 (
1)
1-
11
#775
0)
#776
1)
0-
01
#777
0)
#778
b01010 &
b001001100011 '
b110110011100 (
1)
1-
11
#779
0)
#780
1)
0-
01
#781
0)
0+
1,
#782
b01011 &
b010011000110 '
b101100111001 (
1)
1-
11
#783
0)
#784
1)
0-
01
#785
0)
#786
b01100 &
b100110001100 '
b011001110011 (
1)
1-
11
#787
0)
#788
1)
0-
01
#789
0)
#790
b01101 &
b001100011000 '
b110011100111 (
1)
1-
11
#791
0)
1+
0,
#792
1)
0-
01
#793
0)
#794
b01110 &
b011000110001 '
b100111001110 (
1)
1-
11
#795
0)
#796
1)
0-
01
#797
0)
#798
b01111 &
b110001100011 '
b001110011100 (
1)
1-
11
#799
0)
#800
1)
0-
01
#801
0)
0+
1,
#802
b10000 &
b100011000110 '
b011100111001 (
1)
1-
11
#803
0)
#804
1)
0-
01
#805
0)
#806
b10001 &
b000110001100 '
b111001110011 (
1)
1-
11
#807
0)
#808
1)
0-
01
#809
0)
#810
b000110001100 #
b111001110011 $
1%
b00000 &
1)
1-
1.
0/
11
#811
0)
#812
1)
01
#813
0)
#814
0%
b00001 &
1)
0.
11
#815
0)
1+
0,
#816
1)
0-
01
#817
0)
#818
b00010 &
b001100011001 '
b110011100110 (
1)
1-
11
#819
0)
#820
1)
0-
01
#821
0)
0+
1,
#822
b00011 &
b011000110010 '
b100111001101 (
1)
1-
11
#823
0)
#824
1)
0-
01
#825
0)
#826
b00100 &
b110001100100 '
b001110011011 (
1)
1-
11
#827
0)
#828
1)
0-
01
#829
0)
#830
b00101 &
b100011001000 '
b011100110111 (
1)
1-
11
#831
0)
1+
0,
#832
1)
0-
01
#833
0)
#834
b00110 &
b000110010001 '
b111001101110 (
1)
1-
11
#835
0)
#836
1)
0-
01
#837
0)
#838
b00111 &
b001100100011 '
b110011011100 (
1)
1-
11
#839
0)
#840
1)
0-
01
#841
0)
0+
1,
#842
b01000 &
b011001000110 '
b100110111001 (
1)
1-
11
#843
0)
#844
1)
0-
01
#845
0)
#846
b01001 &
b110010001100 '
b001101110011 (
1)
1-
11
#847
0)
#848
1)
0-
01
#849
0)
#850
b01010 &
b100100011000 '
b011011100111 (
1)
1-
11
#851
0)
1+
0,
#852
1)
0-
01
#853
0)
#854
b01011 &
b001000110001 '
b110111001110 (
1)
1-
11
#855
0)
#856
1)
0-
01
#857
0)
#858
b01100 &
b010001100011 '
b101110011100 (
1)
1-
11
#859
0)
#860
1)
0-
01
#861
0)
0+
1,
#862
b01101 &
b100011000110 '
b011100111001 (
1)
1-
11
#863
0)
#864
1)
0-
01
#865
0)
#866
b01110 &
b000110001100 '
b111001110011 (
1)
1-
11
#867
0)
#868
1)
0-
01
#869
0)
#870
b01111 &
b001100011000 '
b110011100111 (
1)
1-
11
#871
0)
1+
0,
#872
1)
0-
01
#873
0)
#874
b10000 &
b011000110001 '
b100111001110 (
1)
1-
11
#875
0)
#876
1)
0-
01
#877
0)
#878
b10001 &
b110001100011 '
b001110011100 (
1)
1-
11
#879
0)
#880
1)
0-
01
#881
0)
0+
1,
#882
b110001100011 #
b001110011100 $
1%
b00000 &
1)
1-
1.
1/
11
#883
0)
